odoo/addons/shopinvader_sale_order_report_without_price/README.rst
odoo/addons/shopinvader_sale_order_report_without_price/__init__.py
odoo/addons/shopinvader_sale_order_report_without_price/__manifest__.py
odoo/addons/shopinvader_sale_order_report_without_price/i18n/shopinvader_sale_order_report_without_price.pot
odoo/addons/shopinvader_sale_order_report_without_price/readme/CONTRIBUTORS.rst
odoo/addons/shopinvader_sale_order_report_without_price/readme/DESCRIPTION.rst
odoo/addons/shopinvader_sale_order_report_without_price/readme/USAGE.rst
odoo/addons/shopinvader_sale_order_report_without_price/services/__init__.py
odoo/addons/shopinvader_sale_order_report_without_price/services/sale.py
odoo/addons/shopinvader_sale_order_report_without_price/static/description/index.html
odoo/addons/shopinvader_sale_order_report_without_price/tests/__init__.py
odoo/addons/shopinvader_sale_order_report_without_price/tests/test_sale_download.py
odoo14_addon_shopinvader_sale_order_report_without_price-14.0.1.0.1.dist-info/METADATA
odoo14_addon_shopinvader_sale_order_report_without_price-14.0.1.0.1.dist-info/WHEEL
odoo14_addon_shopinvader_sale_order_report_without_price-14.0.1.0.1.dist-info/top_level.txt
odoo14_addon_shopinvader_sale_order_report_without_price-14.0.1.0.1.dist-info/RECORD
